aeroframe/__init__.py
aeroframe/__version__.py
aeroframe/_wrappers/__init__.py
aeroframe/_wrappers/cfd/__init__.py
aeroframe/_wrappers/cfd/dummy.py
aeroframe/_wrappers/cfd/pytornado.py
aeroframe/_wrappers/structure/__init__.py
aeroframe/_wrappers/structure/dummy.py
aeroframe/_wrappers/structure/framat.py
aeroframe/analyses/__init__.py
aeroframe/analyses/static.py
aeroframe/data/__init__.py
aeroframe/data/datafields.py
aeroframe/data/shared.py
aeroframe/fileio/__init__.py
aeroframe/fileio/serialise.py
aeroframe/fileio/settings.py
aeroframe/interpol/__init__.py
aeroframe/interpol/translate.py
aeroframe/plot/__init__.py
aeroframe/plot/makeplot.py
aeroframe/stdfun/__init__.py
aeroframe/stdfun/init.py
aeroframe/stdfun/plot.py
aeroframe/stdfun/run.py
aeroframe/templates/__init__.py
aeroframe/templates/wrappers.py
aeroframe-0.1.2.data/scripts/aeroframe
aeroframe-0.1.2.dist-info/LICENSE.txt
aeroframe-0.1.2.dist-info/METADATA
aeroframe-0.1.2.dist-info/WHEEL
aeroframe-0.1.2.dist-info/top_level.txt
aeroframe-0.1.2.dist-info/RECORD
