Metadata-Version: 2.1
Name: aeroframe
Version: 0.1.2
Summary: AeroFrame (Aeroelastic Framework)
Home-page: https://github.com/airinnova/aeroframe
Author: Aaron Dettmann
Author-email: dettmann@kth.se
License: Apache License 2.0
Platform: UNKNOWN
Classifier: Programming Language :: Python :: 3
Classifier: Programming Language :: Python :: 3.6
Classifier: License :: OSI Approved :: Apache Software License
Classifier: Operating System :: OS Independent
Classifier: Environment :: Console
Classifier: Intended Audience :: Developers
Classifier: Intended Audience :: Education
Classifier: Intended Audience :: Science/Research
Classifier: Topic :: Scientific/Engineering
Classifier: Topic :: Scientific/Engineering :: Physics
Requires-Python: >=3.6.0
Requires-Dist: commonlibs (>=0.3.4)
Requires-Dist: matplotlib (>=3.0.2)
Provides-Extra: examples
Requires-Dist: framat (==0.3.0) ; extra == 'examples'
